degiro_analytics/DeGiroWrapper.py
degiro_analytics/__init__.py
degiro_analytics/utils.py
degiro_analytics-0.3.2.dist-info/METADATA
degiro_analytics-0.3.2.dist-info/WHEEL
degiro_analytics-0.3.2.dist-info/licenses/LICENSE
degiro_analytics-0.3.2.dist-info/RECORD
