Metadata-Version: 2.1
Name: degiro_analytics
Version: 0.3.2
Summary: DeGiro Analytics and API tools
Project-URL: Documentation, https://github.com/unknown/degiro-analytics#readme
Project-URL: Issues, https://github.com/unknown/degiro-analytics/issues
Project-URL: Source, https://github.com/unknown/degiro-analytics
Author-email: Dmytro Pokidin <dmytro.pokidin@gmail.com>
License-File: LICENSE
Classifier: Development Status :: 4 - Beta
Classifier: Programming Language :: Python
Classifier: Programming Language :: Python :: 3.7
Classifier: Programming Language :: Python :: 3.8
Classifier: Programming Language :: Python :: 3.9
Classifier: Programming Language :: Python :: 3.10
Classifier: Programming Language :: Python :: 3.11
Classifier: Programming Language :: Python :: Implementation :: CPython
Classifier: Programming Language :: Python :: Implementation :: PyPy
Requires-Python: >=3.7
Requires-Dist: pandas>=1.4.2
Requires-Dist: requests>=2.27.1
